<?xml version="1.0" encoding="utf-8"?>
<ScadaDataDictionaries>
  <Dictionary key="Common">
    <Phrase key="ProductName">Cloud SCADA</Phrase>
    <Phrase key="InfoCaption">Информације</Phrase>
    <Phrase key="QuestionCaption">Питање</Phrase>
    <Phrase key="ErrorCaption">Грешка</Phrase>
    <Phrase key="WarningCaption">Упозорење</Phrase>
    <Phrase key="Error">Грешка</Phrase>
    <Phrase key="ErrorWithColon">Грешка:</Phrase>
    <Phrase key="UnhandledException">Необрађен изузетак</Phrase>
    <Phrase key="SaveSettingsConfirm">Подешавања су измењена.  Да сачувате промене?</Phrase>
    <Phrase key="FileNotFound">Фајл није пронађен.</Phrase>
    <Phrase key="DirNotExists">Именик не постоји.</Phrase>
    <Phrase key="NamedFileNotFound">Датотека {0} није пронађена.</Phrase>
    <Phrase key="NamedDirNotExists">Директоријум {0} не постоји.</Phrase>
    <Phrase key="BaseDATDir">Конфигурациона база података у директоријуму формата DAT</Phrase>
    <Phrase key="BaseDATDirNotExists">Конфигурациона база података у директоријуму DAT формата не постоји.</Phrase>
    <Phrase key="ChooseBaseDATDir">Изаберите конфигурациону базу података у директоријуму формата DAT</Phrase>
    <Phrase key="LoadAppSettingsError">Грешка при учитавању подешавања апликације</Phrase>
    <Phrase key="SaveAppSettingsError">Грешка при чувању подешавања апликације</Phrase>
    <Phrase key="LoadCommSettingsError">Грешка при учитавању подешавања везе са сервером</Phrase>
    <Phrase key="SaveCommSettingsError">Грешка при чувању подешавања везе са сервером</Phrase>
    <Phrase key="GridDataError">Грешка у подацима</Phrase>
    <Phrase key="IntegerRequired">Потребан је цео број.</Phrase>
    <Phrase key="IntegerRangingRequired">Потребан је цео број од {0} до {1}.</Phrase>
    <Phrase key="RealRequired">Потребан је прави број.</Phrase>
    <Phrase key="NonemptyRequired">Потребна је непразна вредност.</Phrase>
    <Phrase key="DateTimeRequired">Датум и време су обавезни.</Phrase>
    <Phrase key="LineLengthLimit">Дужина стринга мора бити {0} симбола или мање.</Phrase>
    <Phrase key="NotNumber">&quot;{0}&quot; није број.</Phrase>
    <Phrase key="NotHexadecimal">Стринг није һексадецималан.</Phrase>
    <Phrase key="LoadImageError">Грешка при учитавању слике из датотеке:&#13;&#10;{0}</Phrase>
    <Phrase key="LoadHyperlinkError">Грешка при учитавању һипервезе из датотеке:&#13;&#10;{0}</Phrase>
    <Phrase key="IncorrectFileFormat">Нетачан формат датотеке.</Phrase>
    <Phrase key="NoData">Нема података</Phrase>
    <Phrase key="NoRights">Недовољна права.</Phrase>
    <Phrase key="IncorrectXmlNodeVal">Нетачна вредност XML чвора &quot;{0}&quot;.</Phrase>
    <Phrase key="IncorrectXmlAttrVal">Нетачна вредност XML атрибута &quot;{0}&quot;.</Phrase>
    <Phrase key="IncorrectXmlParamVal">Нетачна вредност параметра &quot;{0}&quot;.</Phrase>
    <Phrase key="XmlNodeNotFound">XML чвор &quot;{0}&quot; није пронађен унутар чвора &quot;{1}&quot;.</Phrase>
    <Phrase key="EventAck">да</Phrase>
    <Phrase key="EventNotAck">Не</Phrase>
    <Phrase key="IncorrectCmdVal">Нетачна вредност команде.</Phrase>
    <Phrase key="IncorrectCmdData">Нетачни подаци команде.</Phrase>
    <Phrase key="CmdTypeTable">Типови команди</Phrase>
    <Phrase key="CmdValTable">Командне вредности</Phrase>
    <Phrase key="CnlTypeTable">Типови канала</Phrase>
    <Phrase key="CommLineTable">Комуникационе линије</Phrase>
    <Phrase key="CtrlCnlTable">Излазни канали</Phrase>
    <Phrase key="EvTypeTable">Врсте догађаја</Phrase>
    <Phrase key="FormatTable">Формати бројева</Phrase>
    <Phrase key="FormulaTable">Формуле</Phrase>
    <Phrase key="InCnlTable">Улазни канали</Phrase>
    <Phrase key="InterfaceTable">Интерфејс</Phrase>
    <Phrase key="KPTable">Уређаји</Phrase>
    <Phrase key="KPTypeTable">Типови уређаја</Phrase>
    <Phrase key="ObjTable">Објекти</Phrase>
    <Phrase key="ParamTable">Количине</Phrase>
    <Phrase key="RightTable">права</Phrase>
    <Phrase key="RoleTable">Улоге</Phrase>
    <Phrase key="RoleRefTable">Наслеђивање улога</Phrase>
    <Phrase key="UnitTable">Јединице</Phrase>
    <Phrase key="UserTable">Корисници</Phrase>
    <Phrase key="ContinuePendingSvcState">наставити на чекању</Phrase>
    <Phrase key="PausedSvcState">паузирао</Phrase>
    <Phrase key="PausePendingSvcState">пауза на чекању</Phrase>
    <Phrase key="RunningSvcState">трчање</Phrase>
    <Phrase key="StartPendingSvcState">почети на чекању</Phrase>
    <Phrase key="StoppedSvcState">стао</Phrase>
    <Phrase key="StopPendingSvcState">зауставити чекање</Phrase>
    <Phrase key="NotInstalledSvcState">није инсталирана</Phrase>
  </Dictionary>
  <Dictionary key="KeyGen">
    <Phrase key="StringIsNotHex">Стринг није һексадецималан.</Phrase>
    <Phrase key="CompCodeWithError">Рачунски код садржи запис грешке.</Phrase>
    <Phrase key="DecodeCompCodeError">Грешка при декодирању рачунарског кода</Phrase>
    <Phrase key="RetrieveKeyInfoError">Грешка при преузимању информација о кључу за регистрацију</Phrase>
    <Phrase key="IncorrectKeyLength">Дужина регистрационог кључа је нетачна.</Phrase>
    <Phrase key="IncorrectKeyInfo">Подаци о кључу за регистрацију су нетачни.</Phrase>
    <Phrase key="ValidKeyStatus">Регистрациони кључ је важећи</Phrase>
    <Phrase key="ValidWithWarnKeyStatus">Регистрациони кључ је важећи.  Датум истека је {0}</Phrase>
    <Phrase key="NotValidKeyStatus">Регистрациони кључ није важећи</Phrase>
    <Phrase key="ExpiredKeyStatus">Регистрациони кључ је истекао {0}</Phrase>
    <Phrase key="EmptyKeyStatus">Кључ за регистрацију је празан</Phrase>
    <Phrase key="KeyWithErrorStatus">Регистрациони кључ садржи запис грешке</Phrase>
    <Phrase key="IncorrectKeyStatus">Кључ за регистрацију је нетачан</Phrase>
    <Phrase key="KeyFileNotFoundError">Датотека кључа за регистрацију {0} није пронађена.</Phrase>
    <Phrase key="LoadCompCodeError">Грешка при учитавању рачунарског кода</Phrase>
    <Phrase key="SaveCompCodeError">Грешка при чувању рачунарског кода</Phrase>
    <Phrase key="LoadKeyError">Грешка при учитавању кључа за регистрацију</Phrase>
    <Phrase key="SaveKeyError">Грешка при чувању кључа за регистрацију</Phrase>
    <Phrase key="CheckRegistration">Проверите регистрацију &quot;{0}&quot;:</Phrase>
    <Phrase key="CompCodeIs">Код рачунара: {0}</Phrase>
    <Phrase key="RegistrationFailed">Регистрација није успела.</Phrase>
    <Phrase key="RegistrationFailedFor">Регистрација за &quot;{0}&quot; није успела.</Phrase>
  </Dictionary>
  <Dictionary key="KeyGen.UI">
    <Phrase key="lblCompCode">Рачунарски код</Phrase>
    <Phrase key="lblCompCodeTip">Поново покрените услугу да бисте добили компјутерски код.</Phrase>
    <Phrase key="lblRegKey">Кључ за регистрацију</Phrase>
    <Phrase key="llblGetPermanentKey">Купите трајни кључ</Phrase>
    <Phrase key="llblGetTrialKey">Узмите пробни кључ</Phrase>
    <Phrase key="lblKeyStatus">Кључни статус</Phrase>
  </Dictionary>
</ScadaDataDictionaries>